dlPDF/__init__.py
dlPDF/fetch_pdf.py
dlPDF/test.py
simple/__init__.py
simple/fetch_pdf.py
simple/test.py
dlPDF-0.1.4.dist-info/METADATA
dlPDF-0.1.4.dist-info/WHEEL
dlPDF-0.1.4.dist-info/top_level.txt
dlPDF-0.1.4.dist-info/RECORD
