Metadata-Version: 2.1
Name: dlPDF
Version: 0.1.4
Summary: A simple package with a single function
Home-page: 
Author: Sam Manuel
Author-email: 
Classifier: Programming Language :: Python :: 3
Classifier: License :: OSI Approved :: MIT License
Classifier: Operating System :: OS Independent
Requires-Python: >=3.6
